potnia/__init__.py
potnia/data/akkadian.yaml
potnia/data/arabic.yaml
potnia/data/hittite.yaml
potnia/data/linear_a.yaml
potnia/data/linear_b.yaml
potnia/data/luwian.yaml
potnia/data/potnia.bib
potnia/data.py
potnia/enums.py
potnia/main.py
potnia/script.py
potnia/scripts/__init__.py
potnia/scripts/akkadian.py
potnia/scripts/arabic.py
potnia/scripts/hittite.py
potnia/scripts/linear_a.py
potnia/scripts/linear_b.py
potnia/scripts/luwian.py
potnia-0.4.1.dist-info/LICENSE
potnia-0.4.1.dist-info/METADATA
potnia-0.4.1.dist-info/WHEEL
potnia-0.4.1.dist-info/entry_points.txt
potnia-0.4.1.dist-info/RECORD
