Metadata-Version: 2.3
Name: potnia
Version: 0.4.1
Summary: Potnia is an open-source Python library designed to convert Romanized transliterations of ancient texts into Unicode representations of ther respective native scripts..
License: Apache-2.0
Keywords: linear a,linear b,sumerian,akkadian,cuneiform,unicode
Author: Emily Tour
Author-email: esmtour@gmail.com
Requires-Python: >=3.10,<3.13
Classifier: Intended Audience :: Science/Research
Classifier: License :: OSI Approved :: Apache Software License
Classifier: Programming Language :: Python :: 3
Classifier: Programming Language :: Python :: 3.10
Classifier: Programming Language :: Python :: 3.11
Classifier: Programming Language :: Python :: 3.12
Classifier: Topic :: Software Development :: Libraries :: Python Modules
Requires-Dist: guigaga (>=0.0.5)
Requires-Dist: numpy (<2)
Requires-Dist: pybtex (>=0.24.0)
Requires-Dist: pybtexnbib (>=0.1.1)
Requires-Dist: pyyaml (>=6.0.1,<7.0.0)
Requires-Dist: setuptools (>=75.8.0,<76.0.0)
Requires-Dist: typer (>=0.12.5,<0.13.0)
Project-URL: Documentation, https://AncientNLP.github.io/potnia
Project-URL: Homepage, https://github.com/AncientNLP/potnia/
Project-URL: Repository, https://github.com/AncientNLP/potnia/
